setup.py
cavejohnson/__init__.py
cavejohnson.egg-info/PKG-INFO
cavejohnson.egg-info/SOURCES.txt
cavejohnson.egg-info/dependency_links.txt
cavejohnson.egg-info/entry_points.txt
cavejohnson.egg-info/requires.txt
cavejohnson.egg-info/top_level.txt