Metadata-Version: 1.1
Name: cavejohnson
Version: 1.1
Summary: Teach Xcode 6 CI new tricks
Home-page: http://github.com/drewcrawford/cavejohnson
Author: Drew Crawford
Author-email: drew@sealedabstract.com
License: UNKNOWN
Platform: UNKNOWN
Classifier: Development Status :: 5 - Production/Stable
Classifier: Environment :: Console
Classifier: Environment :: MacOS X
Classifier: Intended Audience :: Developers
Classifier: Intended Audience :: Information Technology
Classifier: Intended Audience :: System Administrators
Classifier: License :: OSI Approved :: MIT License
Classifier: Operating System :: MacOS :: MacOS X
Classifier: Programming Language :: Python :: 3 :: Only
Classifier: Programming Language :: Python :: 3.4
Classifier: Topic :: Software Development :: Build Tools
Classifier: Topic :: Software Development :: Testing
